cknife/__init__.py
cknife-0.0.1.dist-info/LICENSE
cknife-0.0.1.dist-info/METADATA
cknife-0.0.1.dist-info/WHEEL
cknife-0.0.1.dist-info/top_level.txt
cknife-0.0.1.dist-info/RECORD
