Metadata-Version: 2.1
Name: cknife
Version: 0.0.1
Summary: cknife python module
Home-page: https://github.com/summershrimp/cknife
Author: Yibai Zhang
Author-email: xm1994@gmail.com
License: UNKNOWN
Platform: UNKNOWN
Classifier: Programming Language :: Python :: 3
Classifier: License :: OSI Approved :: GNU General Public License v2 (GPLv2)
Classifier: Operating System :: OS Independent
